redstone/__init__.py
redstone/auth.py
redstone/client.py
redstone/crn.py
redstone/crypto/__init__.py
redstone/crypto/__main__.py
redstone/keyprotect/__init__.py
redstone/keyprotect/cli.py
test/__init__.py
test/integration/__init__.py
test/integration/self_signed_cert.py
test/integration/test_keyprotect.py
test/integration/test_resourcecontroller.py
test/unit/__init__.py
test/unit/redstone/__init__.py
test/unit/redstone/test_auth.py
redstone-0.6.1.dist-info/LICENSE
redstone-0.6.1.dist-info/METADATA
redstone-0.6.1.dist-info/WHEEL
redstone-0.6.1.dist-info/entry_points.txt
redstone-0.6.1.dist-info/top_level.txt
redstone-0.6.1.dist-info/RECORD
