Metadata-Version: 2.1
Name: redstone
Version: 0.6.1
Summary: A Pythonic IBM Cloud SDK
Home-page: https://github.com/IBM/redstone
Author: Mathew Odden
Author-email: mathewrodden@gmail.com
Classifier: Programming Language :: Python :: 3
Classifier: Programming Language :: Python :: 3.6
Classifier: Programming Language :: Python :: 3.7
Classifier: License :: OSI Approved :: Apache Software License
Requires-Python: >=3.6
License-File: LICENSE
Requires-Dist: requests[security]
Requires-Dist: cryptography
Provides-Extra: docs
Requires-Dist: sphinx (>=3.1) ; extra == 'docs'
Requires-Dist: sphinx-rtd-theme ; extra == 'docs'
